corset/__init__.py
corset/analysis.py
corset/config.py
corset/core.py
corset/plot.py
corset/solver.py
beam_corset-0.1.1.dist-info/METADATA
beam_corset-0.1.1.dist-info/WHEEL
beam_corset-0.1.1.dist-info/licenses/LICENSE
beam_corset-0.1.1.dist-info/RECORD
