Metadata-Version: 2.4
Name: beam-corset
Version: 0.1.1
Summary: Beam Corset is a Gaussian optics mode matching tool made for use in Jupyter notebooks.
Project-URL: Source, https://github.com/lkies/corset
Project-URL: Documentation, https://lkies.github.io/corset
Author-email: Lorenz Kies <dev@lkies.net>
License-Expression: BSD-3-Clause
License-File: LICENSE
Classifier: Intended Audience :: Science/Research
Classifier: License :: OSI Approved :: BSD License
Classifier: Programming Language :: Python :: 3
Classifier: Programming Language :: Python :: 3 :: Only
Classifier: Programming Language :: Python :: 3.11
Requires-Python: >=3.11
Requires-Dist: matplotlib<4,>=3.10.7
Requires-Dist: numpy<3,>=2.3.4
Requires-Dist: pandas<3,>=2.3.3
Requires-Dist: scipy<2,>=1.16.3
